cbsodata4/__init__.py
cbsodata4/catalogs.py
cbsodata4/config.py
cbsodata4/data_processor.py
cbsodata4/dataset_search.py
cbsodata4/datasets.py
cbsodata4/date_handler.py
cbsodata4/downloader.py
cbsodata4/httpx_client.py
cbsodata4/labeler.py
cbsodata4/metadata.py
cbsodata4/observations.py
cbsodata4/query_builder.py
cbsodata4/unit_handler.py
cbsodata4-0.1.3.dist-info/METADATA
cbsodata4-0.1.3.dist-info/WHEEL
cbsodata4-0.1.3.dist-info/entry_points.txt
cbsodata4-0.1.3.dist-info/licenses/LICENSE
cbsodata4-0.1.3.dist-info/RECORD
