Metadata-Version: 2.4
Name: cbsodata4
Version: 0.1.3
Summary: Python package to access the OData4 interface of data and metadata of Statistics Netherlands (CBS)
Author-email: Dennis Albers <dennis_foss@tutan.de>
License-Expression: Apache-2.0
License-File: LICENSE
Requires-Python: >=3.10
Requires-Dist: httpx>=0.28.1
Requires-Dist: pandas>=2.2.3
Requires-Dist: pyarrow>=19.0.1
